punchcards/__init__.py
punchcards/cli.py
punchcards/normalize.py
punchcards/punchcard.py
punchcards-0.3.3.dist-info/LICENSE.txt
punchcards-0.3.3.dist-info/METADATA
punchcards-0.3.3.dist-info/WHEEL
punchcards-0.3.3.dist-info/entry_points.txt
punchcards-0.3.3.dist-info/top_level.txt
punchcards-0.3.3.dist-info/RECORD
